bubus/__init__.py
bubus/helpers.py
bubus/logging.py
bubus/models.py
bubus/service.py
bubus/compatible_utils/__init__.py
bubus/compatible_utils/asyncio_timeout.py
bubus_py310x-1.3.0.dist-info/METADATA
bubus_py310x-1.3.0.dist-info/WHEEL
bubus_py310x-1.3.0.dist-info/licenses/LICENSE
bubus_py310x-1.3.0.dist-info/RECORD
