Metadata-Version: 2.4
Name: bubus-py310x
Version: 1.3.0
Summary: Advanced Pydantic-powered event bus with async support
Project-URL: Repository, https://github.com/abhijeetkaze/bubus
Author: Nick Sweeting, Abhijeet Mohanta
License-File: LICENSE
Classifier: License :: OSI Approved :: MIT License
Classifier: Operating System :: OS Independent
Classifier: Programming Language :: Python :: 3
Requires-Python: <4.0,>=3.10
Requires-Dist: aiofiles>=24.1.0
Requires-Dist: anyio>=4.9.0
Requires-Dist: portalocker>=2.7.0
Requires-Dist: pydantic>=2.11.5
Requires-Dist: typing-extensions>=4.12.2
Requires-Dist: uuid7>=0.1.0
